[
  {
    "name": "Ship_0",
    "width": 8,
    "height": 8,
    "pixels": [
      "........",
      "........",
      "...XX...",
      "..XXXX..",
      "..XXXX..",
      "...XX...",
      "........",
      "...XX..."
    ]
  },
  {
    "name": "Ship_1",
    "width": 8,
    "height": 8,
    "pixels": [
      "........",
      "........",
      "...XX...",
      "..XXXX..",
      "..XXXX..",
      "...XX...",
      "........",
      "....XX.."
    ]
  },
  {
    "name": "Ship_2",
    "width": 8,
    "height": 8,
    "pixels": [
      "........",
      "........",
      "...XX...",
      "..XXXX..",
      "..XXXX..",
      "...XX...",
      "......X.",
      ".....X.."
    ]
  },
  {
    "name": "Ship_3",
    "width": 8,
    "height": 8,
    "pixels": [
      "........",
      "........",
      "...XX...",
      "..XXXX..",
      "..XXXX..",
      "...XX..X",
      "......X.",
      "........"
    ]
  },
  {
    "name": "Ship_4",
    "width": 8,
    "height": 8,
    "pixels": [
      "........",
      "........",
      "...XX...",
      "..XXXX..",
      "..XXXX.X",
      "...XX..X",
      "........",
      "........"
    ]
  },
  {
    "name": "Ship_5",
    "width": 8,
    "height": 8,
    "pixels": [
      "........",
      "........",
      "...XX...",
      "..XXXX.X",
      "..XXXX.X",
      "...XX...",
      "........",
      "........"
    ]
  },
  {
    "name": "Ship_6",
    "width": 8,
    "height": 8,
    "pixels": [
      "........",
      "........",
      "...XX..X",
      "..XXXX.X",
      "..XXXX..",
      "...XX...",
      "........",
      "........"
    ]
  },
  {
    "name": "Ship_7",
    "width": 8,
    "height": 8,
    "pixels": [
      "........",
      "......X.",
      "...XX..X",
      "..XXXX..",
      "..XXXX..",
      "...XX...",
      "........",
      "........"
    ]
  },
  {
    "name": "Ship_8",
    "width": 8,
    "height": 8,
    "pixels": [
      ".....X..",
      "......X.",
      "...XX...",
      "..XXXX..",
      "..XXXX..",
      "...XX...",
      "........",
      "........"
    ]
  },
  {
    "name": "Ship_9",
    "width": 8,
    "height": 8,
    "pixels": [
      "....XX..",
      "........",
      "...XX...",
      "..XXXX..",
      "..XXXX..",
      "...XX...",
      "........",
      "........"
    ]
  },
  {
    "name": "Ship_10",
    "width": 8,
    "height": 8,
    "pixels": [
      "...XX...",
      "........",
      "...XX...",
      "..XXXX..",
      "..XXXX..",
      "...XX...",
      "........",
      "........"
    ]
  },
  {
    "name": "Ship_11",
    "width": 8,
    "height": 8,
    "pixels": [
      "..XX....",
      "........",
      "...XX...",
      "..XXXX..",
      "..XXXX..",
      "...XX...",
      "........",
      "........"
    ]
  },
  {
    "name": "Ship_12",
    "width": 8,
    "height": 8,
    "pixels": [
      "..X.....",
      ".X......",
      "...XX...",
      "..XXXX..",
      "..XXXX..",
      "...XX...",
      "........",
      "........"
    ]
  },
  {
    "name": "Ship_13",
    "width": 8,
    "height": 8,
    "pixels": [
      "........",
      ".X......",
      "X..XX...",
      "..XXXX..",
      "..XXXX..",
      "...XX...",
      "........",
      "........"
    ]
  },
  {
    "name": "Ship_14",
    "width": 8,
    "height": 8,
    "pixels": [
      "........",
      "........",
      "X..XX...",
      "X.XXXX..",
      "..XXXX..",
      "...XX...",
      "........",
      "........"
    ]
  },
  {
    "name": "Ship_15",
    "width": 8,
    "height": 8,
    "pixels": [
      "........",
      "........",
      "...XX...",
      "X.XXXX..",
      "X.XXXX..",
      "...XX...",
      "........",
      "........"
    ]
  },
  {
    "name": "Ship_16",
    "width": 8,
    "height": 8,
    "pixels": [
      "........",
      "........",
      "...XX...",
      "..XXXX..",
      "X.XXXX..",
      "X..XX...",
      "........",
      "........"
    ]
  },
  {
    "name": "Ship_17",
    "width": 8,
    "height": 8,
    "pixels": [
      "........",
      "........",
      "...XX...",
      "..XXXX..",
      "..XXXX..",
      "X..XX...",
      ".X......",
      "........"
    ]
  },
  {
    "name": "Ship_18",
    "width": 8,
    "height": 8,
    "pixels": [
      "........",
      "........",
      "...XX...",
      "..XXXX..",
      "..XXXX..",
      "...XX...",
      ".X......",
      "..X....."
    ]
  },
  {
    "name": "Ship_19",
    "width": 8,
    "height": 8,
    "pixels": [
      "........",
      "........",
      "...XX...",
      "..XXXX..",
      "..XXXX..",
      "...XX...",
      "........",
      "..XX...."
    ]
  }
]

